pytorch_rse/__init__.py
pytorch_rse/rse.py
pytorch_rse-0.1.0.dist-info/LICENSE.txt
pytorch_rse-0.1.0.dist-info/METADATA
pytorch_rse-0.1.0.dist-info/WHEEL
pytorch_rse-0.1.0.dist-info/top_level.txt
pytorch_rse-0.1.0.dist-info/RECORD
